{"node": {"uuid": "fwCc97N6", "title": "Uber OA", "slug": "uber-oa-by-anonymous_user-9gml", "createdAt": "2025-08-13T16:35:09.434869+00:00", "topicId": 7076426, "hitCount": 2265, "author": {"userSlug": ""}, "tags": [{"name": "Uber", "slug": "uber"}], "topic": {"id": 7076426, "commentCount": 28}, "reactions": [{"count": 8, "reactionType": "UPVOTE"}]}, "article": {"uuid": "fwCc97N6", "title": "Uber OA", "content": "Hi Everyone,\nI give Uber OA for SDE 1 hiring drive. for those who attempted:\n\n- How many Questions were you able to solve?\n- How would you rate the difficulty level?\n\nDoes anyone have insights about selection criteria?\n", "createdAt": "2025-08-13T16:35:09.434869+00:00", "hitCount": 2265, "author": {"userSlug": ""}, "reactions": [{"count": 8, "reactionType": "UPVOTE"}]}, "comments": [{"id": 3119317, "post": {"id": 10199349, "content": "I saw someone on reddit solving all 3 :sob:\\nI solved 2 and 1 partial. \\nmine were - biohazard, autocomplete, mincostpath. \\n\\nwill 2 full and 1 8/12 pass OA??? ", "voteCount": 2, "creationDate": 1755106391, "author": {"username": "useEffects"}}}, {"id": 3120466, "post": {"id": 10204523, "content": "Has anyone received other updates regarding ", "voteCount": 1, "creationDate": 1755186662, "author": {"username": "devasis_raj"}}}, {"id": 3119294, "post": {"id": 10199270, "content": "I solved 12/15 TC for q1, q2 fully solved  and q3 8/15 solved \\uD83D\\uDE41", "voteCount": 1, "creationDate": 1755105540, "author": {"username": "Varad"}}}, {"id": 3126211, "post": {"id": 10224294, "content": "Any update for anyone on netx round other than waiting list? ", "voteCount": 0, "creationDate": 1755505915, "author": {"username": "sannitya"}}}, {"id": 3121913, "post": {"id": 10210394, "content": "Can u guys share what type questions they were?", "voteCount": 0, "creationDate": 1755278092, "author": {"username": "Farissa21"}}}, {"id": 3120855, "post": {"id": 10206048, "content": "do you guys think it was an OA for everyone that applied or for people who actually passed the resume screening", "voteCount": 0, "creationDate": 1755217855, "author": {"username": "Edgar1618"}}}, {"id": 3119853, "post": {"id": 10201582, "content": "can someone share the questions?", "voteCount": 0, "creationDate": 1755149540, "author": {"username": "atulraju"}}}, {"id": 3119484, "post": {"id": 10200045, "content": "When did you guys receive the test link?", "voteCount": 0, "creationDate": 1755116350, "author": {"username": "ridit_jain19"}}}, {"id": 3119435, "post": {"id": 10199866, "content": "how did you applied?\\n", "voteCount": 0, "creationDate": 1755112687, "author": {"username": "Amit__k"}}}, {"id": 3119433, "post": {"id": 10199856, "content": "all 3 questions i was managed to solve", "voteCount": 0, "creationDate": 1755112440, "author": {"username": "giridharan-v1"}}}, {"id": 3119264, "post": {"id": 10199141, "content": "Hii \\n\\nThe questions were medium to hard\\n\\ni could only solve 1 question completely and other one only half\\n", "voteCount": 0, "creationDate": 1755104197, "author": {"username": "kadalihrv"}}}, {"id": 3119240, "post": {"id": 10199024, "content": "Only one question i was able to solve U??", "voteCount": 0, "creationDate": 1755103086, "author": {"username": "Dhanvishyam_UB"}}}]}