{"category": "interview-experience", "node": {"id": "1996675", "title": "Uber | SDE-2 | Bangalore | March 2022 | Reject", "commentCount": 19, "viewCount": 6922, "post": {"id": 3372136, "creationDate": 1651380506, "voteCount": 11, "author": null}}, "topic": {"id": 1996675, "title": "Uber | SDE-2 | Bangalore | March 2022 | Reject", "viewCount": 6922, "post": {"id": 3372136, "creationDate": 1651380506, "voteCount": 11, "content": "Recruiter reached out over linkedin. Online test was skipped for me. \\n\\n## Round 1 (Domain specialization)\\n- I chose mine as distributed systems\\n- Was asked to implement a concurrency problem. Similar to producer consumer. \\n- Did it pretty well using python, and condition variables\\n(Verdict: Strong hire, as I did really well)\\n\\n## Round 2 (DSA)\\nGot asked this question. \\nThere are N people who want to visit the haunted house. The person will only go if at least L other people will go with him. Additionally, that person doesn\\'t want to go with more than R other people, since it would ruin the experience for them. What is the maximum number of people that can visit the haunted house at one time so that no constraint is violated?\\n\\nSample Input:\\n```\\n// The number of people\\n\\t6 \\n//  L R\\n\\t1 2\\n\\t1 4\\n\\t0 3\\n\\t0 1\\n\\t3 4\\n\\t0 2\\n```\\nSample Output\\n```\\n3\\n```\\nBombed this round very badly. Tried all approaches I could think of. In the last 10 mins came up with a O(n**2) brute force way, with slight hints from him. But wasnt good enough, as interviewer expected O(n) complexity. \\n\\nAfter the round figured its asked from https://www.hackerrank.com/contests/w15/challenges/haunted-house/, and optimal approach was using segment tree. \\n(Verdict: Lean/No hire)\\n\\nFelt even if I clear further rounds, definitely I am going to be lowballed to SDE-1 due to terrible Round 2. Hence discontinued it, as I already had better offers from other places for SDE-2. But recruiter insisted round 1 feedback is great, so continue on. \\n\\n## Round 3 (Hiring manager round)\\n- LP\\n- Previous projects\\n- Explain most challenging project system design etc\\n- (Verdict: Strong hire)\\n\\n## Round 4 (System design)\\n- Explain most challenging project architecture (30 min)\\n- Design uber eats app certain modules (30 min)\\n- Felt I had a great connect to interviewer and he was impressed by my ideas.\\n- (Verdict: Strong hire)\\n\\nFinally, after 1 week heard from recruiter the verdict is no hire. Because round 2 feedback wasnt even lean hire. But no hire. And even if they offered me, would be lowballed over, not matching my competing offers. Because coding round needs to have atleast lean hire. \\n\\nNevertheless, it was a nice learning experience. Hope that in future I will be better practised to solve such weird DSA questions. \\n\\nCompeting offers:\\n- https://leetcode.com/discuss/compensation/1994319/Rubrik-or-G6-or-Bangalore\\n- https://leetcode.com/discuss/compensation/1994328/Coinbase-or-IC4-or-Bangalore\\n- https://leetcode.com/discuss/compensation/1994341/VMWare-or-MTS3-or-Bangalore\\n\\nOther interview experiences:\\nhttps://leetcode.com/discuss/interview-experience/1994403/Coinbase-or-IC-4-or-Bangalore-or-March-2022-or-Offer \\nhttps://leetcode.com/discuss/interview-experience/1962552/Rubrik-or-G6-or-Bangalore-or-March-2022-or-Offer \\nhttps://leetcode.com/discuss/interview-experience/1996706/VMWare-or-MTS-3-or-Bangalore-or-March-2022-or-Offer\\nhttps://leetcode.com/discuss/interview-experience/1996617/AWS-or-SDE-2-or-Bangalore-or-March-2022-or-Offer\\nhttps://leetcode.com/discuss/interview-experience/2001716/Google-or-L4-Reject-L3-Offer-or-Bangalore-or-March-2022\\nhttps://leetcode.com/discuss/interview-experience/2001740/Microsoft-or-SDE2-or-Hyderabad-or-March-2022-or-Reject\\nhttps://leetcode.com/discuss/interview-experience/2001782/Robin.io-or-SDE2-or-Bangalore-or-March-2022-or-Offer\\nhttps://leetcode.com/discuss/interview-experience/2001992/Nutanix-or-SDE-2-or-Bangalore-or-March-2022\\nhttps://leetcode.com/discuss/interview-experience/2002004/Enterpret-or-SDE-2-or-Bangalore-or-March-2022-or-Reject\\n", "author": null}}, "comments": [{"id": 1372801, "post": {"id": 3374140, "content": "My solution for haunting house problem\\n\\n\\\\#include \\\\<vector\\\\>\\n\\\\# include<iostream\\\\>\\nusing namespace std;\\nint main() {\\n    int n;\\n    cin >> n;\\n    vector<vector<int>> vals(n, vector<int>(2, 0));\\n    for (int i = 0; i < n; i++) {\\n        cin >> vals[i][0] >> vals[i][1];\\n\\n        // keeping number of people allowed\\n        // adding himself to allowed people\\n        vals[i][0]++;\\n        vals[i][1]++;\\n    }\\n    // Finally allowed_people[i] says how many people are okay to be in a group with i people. (i>=1)\\n    // start with noting down +1 and -1 in this vector as per list of ranges given\\n    vector<int> allowed_people(n+2, 0);\\n    int result = 0;\\n    for (int i = 0; i < n; i++) {\\n        // val[i][0] is start range and val[i][1]+1 is end of range so keeping values properly\\n        // so that in next iteration we get exact count. using min(n+1) as given range can cross these values\\n        allowed_people[min(n+1,vals[i][0])]++;\\n        allowed_people[min(n+1,vals[i][1]+1)]--;\\n    }\\n    int curcount = 0;\\n    for (int i = 1; i <=n ;i++) {\\n        // curcount says how many people are okay with group of i people including them selves\\n       // suppose 10 people are okay with group of 5 people then we can consider 5 for our result\\n       // suppose only 3 people okay with group of 7 people we can\\'t consider 7 in result.\\n        curcount += allowed_people[i];\\n        if (curcount >= i) {\\n            result = max(result, i);\\n        }\\n    }\\n    cout << result << endl;\\n    return 0;\\n}\\n", "voteCount": 6, "creationDate": 1651406160, "author": {"username": "hareeshghk"}}}, {"id": 1373594, "post": {"id": 3376741, "content": "Uber has gone crazy these days, how is one supposed to come up with linear time complexity in an interview to such probs. ", "voteCount": 2, "creationDate": 1651459398, "author": {"username": "trishanan"}}}, {"id": 3027964, "post": {"id": 9860390, "content": "Line Sweep\\n\\n```\\n\\nint main() {\\n    int n;\\n    cin >> n;\\n    \\n    vector<int> ls(1000000);\\n    \\n    for ( int i =0; i<n; i++ ) {\\n        int l,r;\\n        cin >> l >> r;\\n        ls[l] += 1;\\n        ls[r+1] -= 1;\\n    }\\n    \\n    int ans = 0;\\n    \\n    for ( int i =1; i<1000000; i++ ) {\\n        ls[i] += ls[i-1];\\n    }\\n    \\n    // ls[i] => number of people fine with i people being there\\n\\n    for ( int i = 0; i < 1000000; i++){\\n        if ( ls[i] - 1 >= i )  // Remember you have to decrease a number because L \\'other\\' people, so don\\'t count yourself\\n            ans = max(ans, min(ls[i],i+1));   // You cannot have 9 people coming if all of them are good with 3 people\\n    }\\n    \\n    cout << ans;\\n    \\n    return 0;\\n}\\n\\n```", "voteCount": 0, "creationDate": 1749549338, "author": {"username": "M-Manas-s"}}}, {"id": 1741050, "post": {"id": 4741196, "content": "So there is no chance to get hired if one of the rounds is no hire feedback? I am in a similar situation, my dsa round is no hire but other round went well, is there any chance for the offer? Please tell me your option.", "voteCount": 0, "creationDate": 1672821488, "author": {"username": "Ravikumar-Sharma-K"}}}, {"id": 1531085, "post": {"id": 3928496, "content": "Hey, did they ask you for Round 1 domain specialization choice beforehand? I am told both will be coding rounds by HR but the name of the interview is confusing, so not sure about what HR told me. Should I just prepare for DS/ Algo or revise the concurrency bits as well? ", "voteCount": 0, "creationDate": 1659889423, "author": {"username": "abg16"}}}, {"id": 1447696, "post": {"id": 3628248, "content": "can someone share the domain specialization problem he is talking about? ", "voteCount": 0, "creationDate": 1655789753, "author": {"username": "babasehgalffan"}}}, {"id": 1430223, "post": {"id": 3567233, "content": "Hey, in round 4, were you supposed to design a class diagram or architectural diagram?", "voteCount": 0, "creationDate": 1654841539, "author": {"username": "zeel_1401"}}}, {"id": 1428018, "post": {"id": 3559198, "content": "Isn\\'t Round 2 a variant of Max overlapping intervals problem? Can be done in NLogN then.", "voteCount": 0, "creationDate": 1654712928, "author": {"username": "krazyDiamond"}}}, {"id": 1420602, "post": {"id": 3532899, "content": "Where did you join finally?", "voteCount": 0, "creationDate": 1654332424, "author": {"username": "sonedeyaar"}}}]}