{"category": "interview-question", "node": {"id": "2353817", "title": "UBER SWE INTERN", "commentCount": 10, "viewCount": 596, "post": {"id": 3872830, "creationDate": 1659164279, "voteCount": 0, "author": null}}, "topic": {"id": 2353817, "title": "UBER SWE INTERN", "viewCount": 596, "post": {"id": 3872830, "creationDate": 1659164279, "voteCount": 0, "content": "![image](https://assets.leetcode.com/users/images/fa0292ce-a899-44f7-82c5-bee9e94cc0c0_1659164268.053725.jpeg)\\n\\n![image](https://assets.leetcode.com/users/images/b8bcee1d-f4dc-4947-97c9-9e925781e0c7_1659164268.2472425.jpeg)\\n\\n\\n![image](https://assets.leetcode.com/users/images/00e7a1db-ddfb-426a-b72a-ba8f1316e99f_1659164268.4466865.jpeg)\\n![image](https://assets.leetcode.com/users/images/2723379e-3989-420b-a7a0-ef0102fd5b8e_1659164268.765196.jpeg)\\n![image](https://assets.leetcode.com/users/images/85596a2e-7376-4a1e-bcca-a70b1c1120c6_1659164269.040283.jpeg)\\n![image](https://assets.leetcode.com/users/images/8b6a3644-02ae-4332-9851-c664bdb0424f_1659164268.9104023.jpeg)\\n![image](https://assets.leetcode.com/users/images/f514672f-b4f8-4fc4-b56a-6943140ad101_1659164269.6551127.jpeg)\\n\\ncan anyone help me with these qs", "author": null}}, "comments": [{"id": 1515883, "post": {"id": 3873638, "content": "\\n```\\nlong long contest(string a, string b){\\n    int i=0;\\n    int j=0;\\n\\n    map<char,int> m;\\n    for(int i=0;i<a.size();i++){\\n        m[a[i]]++;\\n    }\\n\\n    for(auto it: b){\\n        if(m.find(it)==m.end()) return -1;\\n    }\\n    \\n    long long ans=0;\\n    while(j!=b.size()){\\n        if(a[i]==b[j]){\\n            j++;\\n        }\\n        i=(i+1)%a.size();\\n        ans++;\\n    }\\n    return ans;\\n}\\n```", "voteCount": 0, "creationDate": 1659174191, "author": {"username": "Pranavchiku"}}}, {"id": 1515852, "post": {"id": 3873536, "content": "second question is nothing but simple creation of minimum spanning tree, I have shown prims algorithm you may even try for kruskals.\\n```\\nint solution(int noOfCities, int noOfRoads, vector<vector<int>> &roadFees){\\n    vector<vector<int>> adj[noOfCities];\\n    for(int i=0;i<noOfRoads;i++){\\n        adj[roadFees[i][0]-1].push_back({roadFees[i][1]-1,roadFees[i][2]});\\n        adj[roadFees[i][1]-1].push_back({roadFees[i][0]-1,roadFees[i][2]});\\n    }\\n\\n    vector<int> key(noOfCities,INT_MAX);\\n    vector<bool> mstSet(noOfCities,false);\\n    vector<int> parent(noOfCities,-1);\\n\\n    key[0]=0;\\n    parent[0]=-1;\\n    priority_queue<pair<int,int>,vector<pair<int,int>>,greater<pair<int,int>>> pq;\\n\\n    pq.push({0,0});\\n\\n    while(!pq.empty()){\\n        int u=pq.top().second;\\n        pq.pop();\\n        mstSet[u]=true;\\n        for(auto it: adj[u]){\\n            int x=it[0];\\n            int weight=it[1];\\n\\n            if(mstSet[x]==false and weight<key[x]){\\n                key[x]=weight;\\n                pq.push({weight,x});\\n                parent[x]=u;\\n            }\\n        }\\n    }\\n\\n    int sum=0;\\n    for(int i=0;i<noOfCities;i++){\\n        sum|=key[i];\\n    }\\n\\n    return sum;\\n\\n}\\n```", "voteCount": 0, "creationDate": 1659172990, "author": {"username": "Pranavchiku"}}}, {"id": 1515736, "post": {"id": 3872954, "content": "<iframe src=\"https://leetcode.com/playground/7zrC7f9u/shared\" frameBorder=\"0\" width=\"400\" height=\"300\"></iframe>\\n", "voteCount": 0, "creationDate": 1659165706, "author": {"username": "kinght_lord"}}}]}