{"category": "interview-question", "node": {"id": "2419269", "title": "Uber | Atlassian | Online | Maximise the budget", "commentCount": 1, "viewCount": 1223, "post": {"id": 3962078, "creationDate": 1660388096, "voteCount": 2, "author": null}}, "topic": {"id": 2419269, "title": "Uber | Atlassian | Online | Maximise the budget", "viewCount": 1223, "post": {"id": 3962078, "creationDate": 1660388096, "voteCount": 2, "content": "Can anyone help me with the question mentioned below : \\n\\nYou are buying a subway sandwich and optimising between possible choices.\\nYou need to choose between following\\n* `b` kind of breads\\n* `s` types of sauces \\n* `v` types of veggies \\n\\n\\nYou need to follow these rules while customising your sandwich\\n* You need exactly 1 bread\\n* You can add 1 or more types of sauces or no sauces at all\\n* You can request same sauce for maximum 2 times\\n* All veggies are free\\n\\nYou will be getting three inputs:\\n1. breadPrices, int array of `b` length where breadPrices[i] is a price of ith bread\\n2. noVeggies, int representing number of veggies available to choose from\\n3. saucePrices, int array of length `s` where each saucePrices[i] is price of ith sauce\\n4. budget, int representing your max budget for the sandwich\\n\\n\\nYou want to customise a sandwich closest to your budget, if there are more than 1 option then choose the one lower than the budget  \\n\\nConstraints:\\n\\n    n == breadPrices.length\\n    m == toppingCosts.length\\n    1 <= n, m <= 100\\n    1 <= breadPrices[i], saucePrices[i] <= 10000\\n    1 <= budget <= 10000\\n\\n\\n\\nExample 1:\\nInput: breadPrices = [1,7], noVeggies = 5, saucePrices = [3,4], budget = 10\\nOutput: 10\\nExplanation: Consider the following combination (all 0-indexed):\\n- Choose bread 1: cost 7\\n- Take 1 of sauce 0: cost 1 x 3 = 3\\n- Take 0 of sauce 1: cost 0 x 4 = 0\\nTotal: 7 + 3 + 0 = 10.\\n\\n\\nI could come up with only the recursive solution, which I fear is not correct even.\\n```\\n    int maxCost = Integer.MAX_VALUE;\\n\\n    public int findMaxCost(int[] breads, int[] sauces, int budget) {\\n        for (int i = 0; i < breads.length; i++) {\\n            int cost = breads[i];\\n            findMinCostRecursion(cost, 0, sauces, budget);\\n        }\\n        return maxCost;\\n    }\\n\\n    private void findMinCostRecursion(int cost, int index, int[] sauces, int budget) {\\n        if (cost > budget) {\\n            return;\\n        }\\n        if (budget - cost <= maxCost) {\\n            maxCost = cost;\\n        }\\n        for (int i = 0; i < sauces.length; i++) {\\n            findMinCostRecursion(cost + sauces[i], i + 1, sauces, budget);\\n            findMinCostRecursion(cost + 2 * sauces[i], i + 1, sauces, budget);\\n            findMinCostRecursion(cost, i + 1, sauces, budget);\\n        }\\n    }\\n```", "author": null}}, "comments": [{"id": 1662711, "post": {"id": 4420523, "content": "Whynot just the selection of bread itself?", "voteCount": 0, "creationDate": 1667020321, "author": {"username": "user9854OG"}}}]}