{"category": "interview-question", "node": {"id": "3544430", "title": "[UBER][Frontend] Can someone please share interview experience for uber india frontend role", "commentCount": 4, "viewCount": 669, "post": {"id": 5447533, "creationDate": 1684576071, "voteCount": 1, "author": null}}, "topic": {"id": 3544430, "title": "[UBER][Frontend] Can someone please share interview experience for uber india frontend role", "viewCount": 669, "post": {"id": 5447533, "creationDate": 1684576071, "voteCount": 1, "content": "Hi, \\n\\ni am looking for interview experience  for Sr Software Engineer -  Frontend for india location.\\n\\nThanks\\n\\n", "author": null}}, "comments": [{"id": 2253101, "post": {"id": 6972270, "content": "Hi OP, can you please share your experience? ", "voteCount": 0, "creationDate": 1707746454, "author": {"username": "rb_codes"}}}, {"id": 2429558, "post": {"id": 7669716, "content": "Sample questions for practise: https://mohit8.gumroad.com/l/ygass\\nor can practise at PrepareFrontend - https://preparefrontend.com", "voteCount": -2, "creationDate": 1717176964, "author": {"username": "moniv9"}}}]}